saltext/yte/__init__.py
saltext/yte/loader.py
saltext/yte/version.py
saltext/yte/renderers/__init__.py
saltext/yte/renderers/yte_mod.py
saltext_yte-1.0.1.dist-info/licenses/LICENSE
saltext_yte-1.0.1.dist-info/METADATA
saltext_yte-1.0.1.dist-info/WHEEL
saltext_yte-1.0.1.dist-info/entry_points.txt
saltext_yte-1.0.1.dist-info/top_level.txt
saltext_yte-1.0.1.dist-info/RECORD
