Metadata-Version: 2.4
Name: saltext.yte
Version: 1.0.1
Summary: Salt Extension for interacting with Yte
Home-page: https://github.com/salt-extensions/saltext-yte
Author: Tyler Levy Conde
Author-email: tyler.levy-conde@broadcom.com
License: Apache Software License
Project-URL: Source, https://github.com/salt-extensions/saltext-yte
Project-URL: Tracker, https://github.com/salt-extensions/saltext-yte/issues
Keywords: salt-extension
Platform: any
Classifier: Programming Language :: Python
Classifier: Programming Language :: Cython
Classifier: Programming Language :: Python :: 3
Classifier: Programming Language :: Python :: 3 :: Only
Classifier: Programming Language :: Python :: 3.5
Classifier: Programming Language :: Python :: 3.6
Classifier: Programming Language :: Python :: 3.7
Classifier: Programming Language :: Python :: 3.8
Classifier: Programming Language :: Python :: 3.9
Classifier: Development Status :: 4 - Beta
Classifier: Intended Audience :: Developers
Classifier: License :: OSI Approved :: Apache Software License
Requires-Python: >=3.5
License-File: LICENSE
Requires-Dist: salt>=3006
Requires-Dist: yte
Requires-Dist: distro
Requires-Dist: looseversion
Requires-Dist: salt>=3006
Requires-Dist: tornado
Requires-Dist: yte
Dynamic: license-file
Dynamic: requires-dist
